pe.v
`timescale 1ns/1ps

module pe #(
    parameter Data_W = 4,
    parameter Psum_W = 9
)(
    input                   clk,
    input                   rst_n,
    input                   clear,

    input      [Data_W-1:0] a_in,
    input      [Data_W-1:0] b_in,
    input      [Psum_W-1:0] cin,

    output reg [Data_W-1:0] a_out,
    output reg [Data_W-1:0] b_out,
    output reg [Psum_W-1:0] cout,

    input                   pe_en,
    input                   load_en,
    input                   load_sel,
    input                   act_sel
);

    reg  [Data_W-1:0]   w0_buf, w1_buf;
    wire [Data_W-1:0]   w_act;
    wire [2*Data_W-1:0] product;
    reg  [Psum_W-1:0]   mul_ext;

    assign w_act   = act_sel ? w1_buf : w0_buf;
    assign product = a_in * w_act;

    always @(*) begin
        mul_ext = 0;
        mul_ext[2*Data_W-1:0] = product;
    end

    always @(posedge clk or negedge rst_n) begin
        if (!rst_n) begin
            w0_buf <= 0;
            w1_buf <= 0;
            a_out  <= 0;
            b_out  <= 0;
            cout   <= 0;
        end 
        else begin
            a_out <= a_in;
            b_out <= b_in;

            if (load_en) begin
                if (load_sel) w1_buf <= b_in;
                else          w0_buf <= b_in;
            end

            if (clear) 
                cout <= 0;
            else if (pe_en) 
                cout <= cin + mul_ext;
            else 
                cout <= cin;
        end
    end

endmodule

array_2x2.v
`timescale 1ns/1ps
`include "pe.v"

module array_2x2 #(
    parameter Data_W = 4,
    parameter Psum_W = 9
)(
    input                   clk,
    input                   rst_n,

    input      [Data_W-1:0] a11_in,
    input      [Data_W-1:0] a21_in,

    input      [Data_W-1:0] b11_in,
    input      [Data_W-1:0] b12_in,

    input       [3:0]       load_en,
    input       [3:0]       load_sel,
    input       [3:0]       act_sel,

    input                   clear,
    input                   pe_en,

    output     [Psum_W-1:0] c21_out,
    output     [Psum_W-1:0] c22_out
);

    wire [Data_W-1:0] a11_out;
    wire [Data_W-1:0] a21_out;
    wire [Data_W-1:0] b11_out;
    wire [Data_W-1:0] b12_out;
    wire [Psum_W-1:0] c11_out;
    wire [Psum_W-1:0] c12_out;


    pe #(
        .Data_W(Data_W),
        .Psum_W(Psum_W)
    ) u_pe11 (
        .clk        (clk),
        .rst_n      (rst_n),

        .a_in       (a11_in),
        .b_in       (b11_in),
        .cin        ({Psum_W{1'b0}}),

        .a_out      (a11_out),
        .b_out      (b11_out),
        .cout       (c11_out),

        .load_en    (load_en[0]),
        .load_sel   (load_sel[0]),
        .act_sel    (act_sel[0]),

        .clear (clear),
        .pe_en (pe_en)
    );

    pe #(
        .Data_W(Data_W),
        .Psum_W(Psum_W)
    ) u_pe12 (
        .clk        (clk),
        .rst_n      (rst_n),

        .a_in       (a11_out),
        .b_in       (b12_in),
        .cin        ({Psum_W{1'b0}}),

        .a_out      (),
        .b_out      (b12_out),
        .cout       (c12_out),

        .load_en    (load_en[1]),
        .load_sel   (load_sel[1]),
        .act_sel    (act_sel[1]),

        .clear (clear),
        .pe_en (pe_en)
    );

    pe #(
        .Data_W(Data_W),
        .Psum_W(Psum_W)
    ) u_pe21 (
        .clk        (clk),
        .rst_n      (rst_n),

        .a_in       (a21_in),
        .b_in       (b11_out),
        .cin        (c11_out),

        .a_out      (a21_out),
        .b_out      (),
        .cout       (c21_out),

        .load_en    (load_en[2]),
        .load_sel   (load_sel[2]),
        .act_sel    (act_sel[2]),

        .clear (clear),
        .pe_en (pe_en)
    );

    pe #(
        .Data_W(Data_W),
        .Psum_W(Psum_W)
    ) u_pe22 (
        .clk        (clk),
        .rst_n      (rst_n),

        .a_in       (a21_out),
        .b_in       (b12_out),
        .cin        (c12_out),

        .a_out      (),
        .b_out      (),
        .cout       (c22_out),

        .load_en    (load_en[3]),
        .load_sel   (load_sel[3]),
        .act_sel    (act_sel[3]),

        .clear (clear),
        .pe_en (pe_en)
    );

endmodule

systolic.v
`timescale 1ns/1ps
`include "array_2x2.v"

module systolic #(
    parameter Data_W = 4,
    parameter Psum_W = 9
)(
    input                   clk,
    input                   rst_n,
    input                   in_valid,

    input      [Data_W-1:0] a11,
    input      [Data_W-1:0] a12,
    input      [Data_W-1:0] a21,
    input      [Data_W-1:0] a22,

    input      [Data_W-1:0] b11,
    input      [Data_W-1:0] b12,
    input      [Data_W-1:0] b21,
    input      [Data_W-1:0] b22,

    output reg [Psum_W-1:0] c11,
    output reg [Psum_W-1:0] c12,
    output reg [Psum_W-1:0] c21,
    output reg [Psum_W-1:0] c22,
    output reg              out_valid
);

    localparam ST_IDLE  = 3'd0;
    localparam ST_PRE0  = 3'd1;
    localparam ST_PRE1  = 3'd2;
    localparam ST_RUN0  = 3'd3;
    localparam ST_RUN1  = 3'd4;
    localparam ST_RUN2  = 3'd5;
    localparam ST_DRAIN = 3'd6;

    reg [2:0] state;

    reg                 cur_valid;
    reg [Data_W-1:0]    cur_a11, cur_a12, cur_a21, cur_a22;
    reg [Data_W-1:0]    cur_b11, cur_b12, cur_b21, cur_b22;

    reg                 nxt_valid;
    reg                 nxt_loaded;
    reg [1:0]           nxt_prog;
    reg [Data_W-1:0]    nxt_a11, nxt_a12, nxt_a21, nxt_a22;
    reg [Data_W-1:0]    nxt_b11, nxt_b12, nxt_b21, nxt_b22;

    reg                 active_bank;
    wire                inactive_bank;

    assign inactive_bank = ~active_bank;

    reg  [Data_W-1:0]   arr_a_top;      // input into PE11 from west
    reg  [Data_W-1:0]   arr_a_bot;      // input into PE21 from west
    reg  [Data_W-1:0]   arr_b_col0;     // input into PE11 from north
    reg  [Data_W-1:0]   arr_b_col1;     // input into PE12 from north

    // bit order: {PE22, PE21, PE12, PE11}
    reg  [3:0]          arr_load_en;    // 0: keep, 1: load
    reg  [3:0]          arr_load_sel;   // 0: load to buf0, 1: load to buf1
    reg  [3:0]          arr_act_sel;    // 0: compute with buf0, 1: compute with buf1   
    reg                 arr_clear;
    reg                 arr_pe_en;

    wire [Psum_W-1:0]   arr_c_row0;
    wire [Psum_W-1:0]   arr_c_row1;

    reg                 do_nxt_p0;
    reg                 do_nxt_p1;
    reg                 do_nxt_p2;
    reg                 do_overlap_run0;

    reg                 pending_c22;
    reg                 drain_has_next;

    array_2x2 #(
        .Data_W (Data_W),
        .Psum_W (Psum_W)
    ) u_array_2x2 (
        .clk      (clk),
        .rst_n    (rst_n),

        .a11_in   (arr_a_top),
        .a21_in   (arr_a_bot),

        .b11_in   (arr_b_col0),
        .b12_in   (arr_b_col1),

        .load_en  (arr_load_en),
        .load_sel (arr_load_sel),
        .act_sel  (arr_act_sel),

        .clear    (arr_clear),
        .pe_en    (arr_pe_en),

        .c21_out  (arr_c_row0),
        .c22_out  (arr_c_row1)
    );

    // overlap scheduling
    always @(*) begin
        do_nxt_p0       = 1'b0;
        do_nxt_p1       = 1'b0;
        do_nxt_p2       = 1'b0;
        do_overlap_run0 = 1'b0;

        case (state)
            ST_RUN0: begin
                if (nxt_valid && !nxt_loaded && (nxt_prog == 2'd0))
                    do_nxt_p0 = 1'b1;
            end

            ST_RUN1: begin
                if (nxt_valid && !nxt_loaded && (nxt_prog == 2'd1))
                    do_nxt_p1 = 1'b1;
            end

            ST_RUN2: begin
                if (nxt_valid && !nxt_loaded && (nxt_prog == 2'd2)) begin
                    do_nxt_p2       = 1'b1;
                    do_overlap_run0 = 1'b1;
                end
            end

            default: begin
            end
        endcase
    end

    // combinational scheduler
    always @(*) begin
        arr_a_top    = {Data_W{1'b0}};
        arr_a_bot    = {Data_W{1'b0}};
        arr_b_col0   = {Data_W{1'b0}};
        arr_b_col1   = {Data_W{1'b0}};

        arr_load_en  = 4'b0000;
        arr_load_sel = 4'b0000;
        arr_act_sel  = {4{active_bank}};

        arr_clear    = 1'b0;
        arr_pe_en    = 1'b0;

        case (state)
            ST_IDLE: begin      // 0
                arr_clear = 1'b0;
            end

            ST_PRE0: begin      // 1
                // col0 -> b21, only PE11 loads current bank
                arr_clear    = 1'b1;
                arr_b_col0   = cur_b21;
                arr_load_en  = 4'b0001;
                arr_load_sel = {1'b0, 1'b0, 1'b0, active_bank};
            end

            ST_PRE1: begin      // 2
                // col0 -> b11, col1 -> b22
                // PE11 / PE12 / PE21 load current bank
                arr_clear    = 1'b1;
                arr_b_col0   = cur_b11;
                arr_b_col1   = cur_b22;
                arr_load_en  = 4'b0111;
                arr_load_sel = {1'b0, active_bank, active_bank, active_bank};
            end

            ST_RUN0: begin      // 3
                arr_pe_en   = 1'b1;
                arr_a_top   = cur_a11;
                arr_a_bot   = {Data_W{1'b0}};
                arr_b_col1  = cur_b12;

                // only PE11 is valid for current op in this cycle
                arr_act_sel = {inactive_bank, inactive_bank, inactive_bank, active_bank};

                if (do_nxt_p0) begin
                    // PE22 / PE12 load current bank
                    // PE11 loads nxt_b21 into inactive bank
                    arr_b_col0   = nxt_b21;
                    arr_load_en  = 4'b1011;
                    arr_load_sel = {active_bank, 1'b0, active_bank, inactive_bank};
                end
                else begin
                    arr_load_en  = 4'b1010;
                    arr_load_sel = {active_bank, 1'b0, active_bank, 1'b0};
                end
            end

            ST_RUN1: begin      // 4, 6
                arr_pe_en   = 1'b1;
                arr_a_top   = cur_a21;
                arr_a_bot   = cur_a12;
                arr_act_sel = {inactive_bank, active_bank, active_bank, active_bank};

                if (do_nxt_p1) begin
                    // preload next step1 into inactive bank
                    arr_b_col0   = nxt_b11;
                    arr_b_col1   = nxt_b22;
                    arr_load_en  = 4'b0111;
                    arr_load_sel = {1'b0, inactive_bank, inactive_bank, inactive_bank};
                end
            end

            ST_RUN2: begin      // 5, 7
                arr_pe_en = 1'b1;

                if (do_overlap_run0) begin
                    // current op final wave on bottom row
                    // next op first wave on PE11 only
                    arr_a_top   = nxt_a11;
                    arr_a_bot   = cur_a22;
                    arr_act_sel = {active_bank, active_bank, active_bank, inactive_bank};

                    // preload next step2 into inactive bank: PE22 / PE12
                    arr_b_col1   = nxt_b12;
                    arr_load_en  = 4'b1010;
                    arr_load_sel = {inactive_bank, 1'b0, inactive_bank, 1'b0};
                end
                else begin
                    // no overlap, still finish current right-column timing
                    arr_a_top   = {Data_W{1'b0}};
                    arr_a_bot   = cur_a22;
                    arr_act_sel = {active_bank, active_bank, active_bank, inactive_bank};
                end
            end

            ST_DRAIN: begin     // 8
                // one extra cycle to flush final PE22 output
                arr_pe_en   = 1'b1;
                arr_a_top   = {Data_W{1'b0}};
                arr_a_bot   = {Data_W{1'b0}};
                arr_act_sel = {active_bank, inactive_bank, inactive_bank, inactive_bank};
            end

            default: begin
                arr_clear = 1'b0;
            end
        endcase
    end

    // sequential logic
    always @(posedge clk or negedge rst_n) begin
        if (!rst_n) begin
            state          <= ST_IDLE;

            cur_valid      <= 1'b0;
            nxt_valid      <= 1'b0;
            nxt_loaded     <= 1'b0;
            nxt_prog       <= 2'd0;

            active_bank    <= 1'b0;

            pending_c22    <= 1'b0;
            drain_has_next <= 1'b0;

            c11            <= {Psum_W{1'b0}};
            c12            <= {Psum_W{1'b0}};
            c21            <= {Psum_W{1'b0}};
            c22            <= {Psum_W{1'b0}};
            out_valid      <= 1'b0;

            cur_a11 <= 0; cur_a12 <= 0; cur_a21 <= 0; cur_a22 <= 0;
            cur_b11 <= 0; cur_b12 <= 0; cur_b21 <= 0; cur_b22 <= 0;

            nxt_a11 <= 0; nxt_a12 <= 0; nxt_a21 <= 0; nxt_a22 <= 0;
            nxt_b11 <= 0; nxt_b12 <= 0; nxt_b21 <= 0; nxt_b22 <= 0;
        end
        else begin
            out_valid <= 1'b0;

            // capture outputs at their real timing points
            if (state == ST_RUN1) begin
                c11 <= arr_c_row0;
            end

            if (state == ST_RUN2) begin
                c12 <= arr_c_row1;
                c21 <= arr_c_row0;
            end

            if (pending_c22 || (state == ST_DRAIN)) begin
                c22 <= arr_c_row1;
                out_valid <= 1'b1;
                pending_c22 <= 1'b0;
            end

            // accept input ops
            if (in_valid) begin
                if (!cur_valid && state == ST_IDLE) begin
                    cur_valid <= 1'b1;

                    cur_a11 <= a11; cur_a12 <= a12;
                    cur_a21 <= a21; cur_a22 <= a22;

                    cur_b11 <= b11; cur_b12 <= b12;
                    cur_b21 <= b21; cur_b22 <= b22;
                end
                else if (!nxt_valid) begin
                    nxt_valid  <= 1'b1;
                    nxt_loaded <= 1'b0;
                    nxt_prog   <= 2'd0;

                    nxt_a11 <= a11; nxt_a12 <= a12;
                    nxt_a21 <= a21; nxt_a22 <= a22;

                    nxt_b11 <= b11; nxt_b12 <= b12;
                    nxt_b21 <= b21; nxt_b22 <= b22;
                end
            end

            if (do_nxt_p0) begin
                nxt_prog <= 2'd1;
            end
            else if (do_nxt_p1) begin
                nxt_prog <= 2'd2;
            end
            else if (do_nxt_p2) begin
                nxt_prog   <= 2'd3;
                nxt_loaded <= 1'b1;
            end

            case (state)
                ST_IDLE: begin
                    if (cur_valid || in_valid)
                        state <= ST_PRE0;
                end

                ST_PRE0: begin
                    state <= ST_PRE1;
                end

                ST_PRE1: begin
                    state <= ST_RUN0;
                end

                ST_RUN0: begin
                    state <= ST_RUN1;
                end

                ST_RUN1: begin
                    state <= ST_RUN2;
                end

                ST_RUN2: begin
                    if (do_overlap_run0) begin
                        // current c22 will appear at next cycle
                        pending_c22 <= 1'b1;

                        cur_valid <= 1'b1;

                        cur_a11 <= nxt_a11; cur_a12 <= nxt_a12;
                        cur_a21 <= nxt_a21; cur_a22 <= nxt_a22;

                        cur_b11 <= nxt_b11; cur_b12 <= nxt_b12;
                        cur_b21 <= nxt_b21; cur_b22 <= nxt_b22;

                        nxt_valid  <= 1'b0;
                        nxt_loaded <= 1'b0;
                        nxt_prog   <= 2'd0;

                        active_bank <= ~active_bank;
                        state <= ST_RUN1;
                    end
                    else begin
                        drain_has_next <= nxt_valid;
                        state <= ST_DRAIN;
                    end
                end

                ST_DRAIN: begin
                    if (drain_has_next) begin
                        cur_valid <= 1'b1;

                        cur_a11 <= nxt_a11; cur_a12 <= nxt_a12;
                        cur_a21 <= nxt_a21; cur_a22 <= nxt_a22;

                        cur_b11 <= nxt_b11; cur_b12 <= nxt_b12;
                        cur_b21 <= nxt_b21; cur_b22 <= nxt_b22;

                        nxt_valid      <= 1'b0;
                        nxt_loaded     <= 1'b0;
                        nxt_prog       <= 2'd0;
                        drain_has_next <= 1'b0;

                        state <= ST_PRE0;
                    end
                    else begin
                        cur_valid      <= 1'b0;
                        drain_has_next <= 1'b0;
                        state <= ST_IDLE;
                    end
                end

                default: begin
                    state <= ST_IDLE;
                end
            endcase
        end
    end

endmodule

tb_systolic.v
`timescale 1ns/1ps

module tb_systolic;

    reg clk;
    reg rst_n;
    reg in_valid;
    reg [3:0] a11, a12, a21, a22;
    reg [3:0] b11, b12, b21, b22;

    wire [8:0] c11, c12, c21, c22;
    wire       out_valid;

    systolic dut (
        .clk(clk), .rst_n(rst_n), .in_valid(in_valid),
        .a11(a11), .a12(a12), .a21(a21), .a22(a22),
        .b11(b11), .b12(b12), .b21(b21), .b22(b22),
        .c11(c11), .c12(c12), .c21(c21), .c22(c22),
        .out_valid(out_valid)
    );

    initial begin
        clk = 0;
        forever #5 clk = ~clk;
    end

    initial begin
        rst_n = 0; in_valid = 0;
        a11=0; a12=0; a21=0; a22=0; b11=0; b12=0; b21=0; b22=0;
        repeat(5) @(posedge clk);
        rst_n = 1;
        @(posedge clk);

        a11=1; a12=2; a21=3; a22=4; b11=5; b12=6; b21=7; b22=8;
        in_valid = 1;
        @(posedge clk);
        in_valid = 0;

        @(posedge clk);
        a11=1; a12=0; a21=0; a22=1; b11=2; b12=3; b21=4; b22=5;
        in_valid = 1;
        @(posedge clk);
        in_valid = 0;

        @(posedge out_valid);
        $display("op1 C=%0d %0d %0d %0d", c11,c12,c21,c22);

        @(posedge out_valid);
        $display("op2 C=%0d %0d %0d %0d", c11,c12,c21,c22);

	#100
        $display("All tests finished.");
        $finish;
    end

    initial begin
        $dumpfile("tb_systolic.vcd");
        $dumpvars(0, tb_systolic);
    end

endmodule

tb_systolic.vcd
$date
	Tue Mar 24 15:26:56 2026
$end
$version
	Icarus Verilog
$end
$timescale
	1ps
$end
$scope module tb_systolic $end
$var wire 1 ! out_valid $end
$var wire 9 " c22 [8:0] $end
$var wire 9 # c21 [8:0] $end
$var wire 9 $ c12 [8:0] $end
$var wire 9 % c11 [8:0] $end
$var reg 4 & a11 [3:0] $end
$var reg 4 ' a12 [3:0] $end
$var reg 4 ( a21 [3:0] $end
$var reg 4 ) a22 [3:0] $end
$var reg 4 * b11 [3:0] $end
$var reg 4 + b12 [3:0] $end
$var reg 4 , b21 [3:0] $end
$var reg 4 - b22 [3:0] $end
$var reg 1 . clk $end
$var reg 1 / in_valid $end
$var reg 1 0 rst_n $end
$scope module dut $end
$var wire 4 1 a11 [3:0] $end
$var wire 4 2 a12 [3:0] $end
$var wire 4 3 a21 [3:0] $end
$var wire 4 4 a22 [3:0] $end
$var wire 4 5 b11 [3:0] $end
$var wire 4 6 b12 [3:0] $end
$var wire 4 7 b21 [3:0] $end
$var wire 4 8 b22 [3:0] $end
$var wire 1 . clk $end
$var wire 1 / in_valid $end
$var wire 1 9 inactive_bank $end
$var wire 1 0 rst_n $end
$var wire 9 : arr_c_row1 [8:0] $end
$var wire 9 ; arr_c_row0 [8:0] $end
$var reg 1 < active_bank $end
$var reg 4 = arr_a_bot [3:0] $end
$var reg 4 > arr_a_top [3:0] $end
$var reg 4 ? arr_act_sel [3:0] $end
$var reg 4 @ arr_b_col0 [3:0] $end
$var reg 4 A arr_b_col1 [3:0] $end
$var reg 1 B arr_clear $end
$var reg 4 C arr_load_en [3:0] $end
$var reg 4 D arr_load_sel [3:0] $end
$var reg 1 E arr_pe_en $end
$var reg 9 F c11 [8:0] $end
$var reg 9 G c12 [8:0] $end
$var reg 9 H c21 [8:0] $end
$var reg 9 I c22 [8:0] $end
$var reg 4 J cur_a11 [3:0] $end
$var reg 4 K cur_a12 [3:0] $end
$var reg 4 L cur_a21 [3:0] $end
$var reg 4 M cur_a22 [3:0] $end
$var reg 4 N cur_b11 [3:0] $end
$var reg 4 O cur_b12 [3:0] $end
$var reg 4 P cur_b21 [3:0] $end
$var reg 4 Q cur_b22 [3:0] $end
$var reg 1 R cur_valid $end
$var reg 1 S do_nxt_p0 $end
$var reg 1 T do_nxt_p1 $end
$var reg 1 U do_nxt_p2 $end
$var reg 1 V do_overlap_run0 $end
$var reg 1 W drain_has_next $end
$var reg 4 X nxt_a11 [3:0] $end
$var reg 4 Y nxt_a12 [3:0] $end
$var reg 4 Z nxt_a21 [3:0] $end
$var reg 4 [ nxt_a22 [3:0] $end
$var reg 4 \ nxt_b11 [3:0] $end
$var reg 4 ] nxt_b12 [3:0] $end
$var reg 4 ^ nxt_b21 [3:0] $end
$var reg 4 _ nxt_b22 [3:0] $end
$var reg 1 ` nxt_loaded $end
$var reg 2 a nxt_prog [1:0] $end
$var reg 1 b nxt_valid $end
$var reg 1 ! out_valid $end
$var reg 1 c pending_c22 $end
$var reg 3 d state [2:0] $end
$scope module u_array_2x2 $end
$var wire 4 e a11_in [3:0] $end
$var wire 4 f a21_in [3:0] $end
$var wire 4 g act_sel [3:0] $end
$var wire 4 h b11_in [3:0] $end
$var wire 4 i b12_in [3:0] $end
$var wire 1 B clear $end
$var wire 1 . clk $end
$var wire 4 j load_en [3:0] $end
$var wire 4 k load_sel [3:0] $end
$var wire 1 E pe_en $end
$var wire 1 0 rst_n $end
$var wire 9 l c22_out [8:0] $end
$var wire 9 m c21_out [8:0] $end
$var wire 9 n c12_out [8:0] $end
$var wire 9 o c11_out [8:0] $end
$var wire 4 p b12_out [3:0] $end
$var wire 4 q b11_out [3:0] $end
$var wire 4 r a21_out [3:0] $end
$var wire 4 s a11_out [3:0] $end
$scope module u_pe11 $end
$var wire 4 t a_in [3:0] $end
$var wire 1 u act_sel $end
$var wire 4 v b_in [3:0] $end
$var wire 9 w cin [8:0] $end
$var wire 1 B clear $end
$var wire 1 . clk $end
$var wire 1 x load_en $end
$var wire 1 y load_sel $end
$var wire 1 E pe_en $end
$var wire 1 0 rst_n $end
$var wire 4 z w_act [3:0] $end
$var wire 8 { product [7:0] $end
$var reg 4 | a_out [3:0] $end
$var reg 4 } b_out [3:0] $end
$var reg 9 ~ cout [8:0] $end
$var reg 9 !" mul_ext [8:0] $end
$var reg 4 "" w0_buf [3:0] $end
$var reg 4 #" w1_buf [3:0] $end
$upscope $end
$scope module u_pe12 $end
$var wire 4 $" a_in [3:0] $end
$var wire 1 %" act_sel $end
$var wire 4 &" b_in [3:0] $end
$var wire 9 '" cin [8:0] $end
$var wire 1 B clear $end
$var wire 1 . clk $end
$var wire 1 (" load_en $end
$var wire 1 )" load_sel $end
$var wire 1 E pe_en $end
$var wire 1 0 rst_n $end
$var wire 4 *" w_act [3:0] $end
$var wire 8 +" product [7:0] $end
$var reg 4 ," a_out [3:0] $end
$var reg 4 -" b_out [3:0] $end
$var reg 9 ." cout [8:0] $end
$var reg 9 /" mul_ext [8:0] $end
$var reg 4 0" w0_buf [3:0] $end
$var reg 4 1" w1_buf [3:0] $end
$upscope $end
$scope module u_pe21 $end
$var wire 4 2" a_in [3:0] $end
$var wire 1 3" act_sel $end
$var wire 4 4" b_in [3:0] $end
$var wire 9 5" cin [8:0] $end
$var wire 1 B clear $end
$var wire 1 . clk $end
$var wire 1 6" load_en $end
$var wire 1 7" load_sel $end
$var wire 1 E pe_en $end
$var wire 1 0 rst_n $end
$var wire 4 8" w_act [3:0] $end
$var wire 8 9" product [7:0] $end
$var reg 4 :" a_out [3:0] $end
$var reg 4 ;" b_out [3:0] $end
$var reg 9 <" cout [8:0] $end
$var reg 9 =" mul_ext [8:0] $end
$var reg 4 >" w0_buf [3:0] $end
$var reg 4 ?" w1_buf [3:0] $end
$upscope $end
$scope module u_pe22 $end
$var wire 4 @" a_in [3:0] $end
$var wire 1 A" act_sel $end
$var wire 4 B" b_in [3:0] $end
$var wire 9 C" cin [8:0] $end
$var wire 1 B clear $end
$var wire 1 . clk $end
$var wire 1 D" load_en $end
$var wire 1 E" load_sel $end
$var wire 1 E pe_en $end
$var wire 1 0 rst_n $end
$var wire 4 F" w_act [3:0] $end
$var wire 8 G" product [7:0] $end
$var reg 4 H" a_out [3:0] $end
$var reg 4 I" b_out [3:0] $end
$var reg 9 J" cout [8:0] $end
$var reg 9 K" mul_ext [8:0] $end
$var reg 4 L" w0_buf [3:0] $end
$var reg 4 M" w1_buf [3:0] $end
$upscope $end
$upscope $end
$upscope $end
$upscope $end
$enddefinitions $end
#0
$dumpvars
b0 M"
b0 L"
b0 K"
b0 J"
b0 I"
b0 H"
b0 G"
b0 F"
0E"
0D"
b0 C"
b0 B"
0A"
b0 @"
b0 ?"
b0 >"
b0 ="
b0 <"
b0 ;"
b0 :"
b0 9"
b0 8"
07"
06"
b0 5"
b0 4"
03"
b0 2"
b0 1"
b0 0"
b0 /"
b0 ."
b0 -"
b0 ,"
b0 +"
b0 *"
0)"
0("
b0 '"
b0 &"
0%"
b0 $"
b0 #"
b0 ""
b0 !"
b0 ~
b0 }
b0 |
b0 {
b0 z
0y
0x
b0 w
b0 v
0u
b0 t
b0 s
b0 r
b0 q
b0 p
b0 o
b0 n
b0 m
b0 l
b0 k
b0 j
b0 i
b0 h
b0 g
b0 f
b0 e
b0 d
0c
0b
b0 a
0`
b0 _
b0 ^
b0 ]
b0 \
b0 [
b0 Z
b0 Y
b0 X
0W
0V
0U
0T
0S
0R
b0 Q
b0 P
b0 O
b0 N
b0 M
b0 L
b0 K
b0 J
b0 I
b0 H
b0 G
b0 F
0E
b0 D
b0 C
0B
b0 A
b0 @
b0 ?
b0 >
b0 =
0<
b0 ;
b0 :
19
b0 8
b0 7
b0 6
b0 5
b0 4
b0 3
b0 2
b0 1
00
0/
0.
b0 -
b0 ,
b0 +
b0 *
b0 )
b0 (
b0 '
b0 &
b0 %
b0 $
b0 #
b0 "
0!
$end
#5000
1.
#10000
0.
#15000
1.
#20000
0.
#25000
1.
#30000
0.
#35000
1.
#40000
0.
#45000
10
1.
#50000
0.
#55000
1x
b1 C
b1 j
b111 @
b111 h
b111 v
1B
b1 d
b1000 Q
b111 P
b110 O
b101 N
b100 M
b11 L
b10 K
b1 J
1R
1/
b1000 -
b1000 8
b111 ,
b111 7
b110 +
b110 6
b101 *
b101 5
b100 )
b100 4
b11 (
b11 3
b10 '
b10 2
b1 &
b1 1
1.
#60000
0.
#65000
1("
16"
b1000 A
b1000 i
b1000 &"
1B
b111 C
b111 j
b101 @
b101 h
b101 v
b111 z
b10 d
b111 ""
b111 q
b111 }
b111 4"
0/
1.
#70000
0.
#75000
1y
1D"
1%"
13"
1A"
b101 !"
06"
b101 z
b0 *"
b0 8"
b1 D
b1 k
b1110 ?
b1110 g
b101 {
b1 >
b1 e
b1 t
1E
0B
b1011 C
b1011 j
b110 A
b110 i
b110 &"
b100 @
b100 h
b100 v
1S
b101 ""
b101 q
b101 }
b101 4"
b1000 0"
b1000 p
b1000 -"
b1000 B"
b111 >"
b111 ;"
b11 d
b101 _
b100 ^
b11 ]
b10 \
b1 [
b1 X
1b
1/
b101 -
b101 8
b100 ,
b100 7
b11 +
b11 6
b10 *
b10 5
b1 )
b1 4
b0 (
b0 3
b0 '
b0 2
1.
#80000
0.
#85000
b110 /"
b1110 ="
b110 +"
b110 *"
b1110 9"
b111 8"
1)"
17"
16"
0%"
03"
0D"
b1111 !"
b10 =
b10 f
b10 2"
1E
b1000 ?
b1000 g
b111 D
b111 k
b111 C
b111 j
b101 A
b101 i
b101 &"
b10 @
b10 h
b10 v
b1111 {
b11 >
b11 e
b11 t
1T
0S
b100 d
b1 a
b1000 L"
b1000 I"
b101 ;"
b110 0"
b110 p
b110 -"
b110 B"
b101 o
b101 ~
b101 5"
b100 #"
b100 q
b100 }
b100 4"
b1 s
b1 |
b1 $"
0/
1.
#90000
0.
#95000
b10000 K"
b10 z
b10000 G"
b1000 F"
1E"
1D"
1u
0A"
0y
07"
0x
06"
b11100 ="
b10 !"
b10010 /"
1E
b1 ?
b1 g
b1010 D
b1010 k
b1010 C
b1010 j
b11 A
b11 i
b11 &"
b0 @
b0 h
b0 v
b11100 9"
b100 =
b100 f
b100 2"
b10 {
b1 >
b1 e
b1 t
1V
1U
0T
b1111 o
b1111 ~
b1111 5"
b10 #"
b10 q
b10 }
b10 4"
b10010 +"
b11 s
b11 |
b11 $"
b110 n
b110 ."
b110 C"
b101 1"
b101 p
b101 -"
b101 B"
b1 ,"
b10011 ;
b10011 m
b10011 <"
b100 ?"
b100 ;"
b10 r
b10 :"
b10 @"
b110 I"
b101 d
b10 a
1.
#100000
0.
#105000
b11 *"
b100 8"
b1000 F"
1%"
13"
0A"
0)"
0E"
0("
0D"
b0 ="
b0 !"
09
1E
b111 ?
b111 g
b0 D
b0 k
b0 C
b0 j
b0 A
b0 i
b0 &"
b0 9"
b0 =
b0 f
b0 2"
b0 {
b0 >
b0 e
b0 t
0V
0U
b100000 K"
b11 /"
b100 d
1<
0b
b101 Q
b100 P
b11 O
b10 N
b1 M
b0 L
b0 K
1c
0`
b0 a
b10011 #
b10011 H
b10110 :
b10110 l
b10110 J"
b101 M"
b101 I"
b10 H"
b101011 ;
b101011 m
b101011 <"
b10 ;"
b100000 G"
b100 r
b100 :"
b100 @"
b10010 n
b10010 ."
b10010 C"
b11 1"
b11 p
b11 -"
b11 B"
b11 ,"
b10 o
b10 ~
b10 5"
b0 q
b0 }
b0 4"
b11 +"
b1 s
b1 |
b1 $"
1.
#110000
0.
#115000
b101 z
b101 F"
0u
b100 ="
1A"
b0 /"
b0 K"
b100 9"
b1 =
b1 f
b1 2"
1E
b1110 ?
b1110 g
b0 o
b0 ~
b0 5"
b0 +"
b0 s
b0 |
b0 $"
b11 n
b11 ."
b11 C"
b0 p
b0 -"
b0 B"
b1 ,"
b10 ;
b10 m
b10 <"
b0 ;"
b0 G"
b0 r
b0 :"
b0 @"
b110010 :
b110010 l
b110010 J"
b11 I"
b100 H"
b101 d
0c
1!
b10110 "
b10110 I
b101011 %
b101011 F
1.
#120000
0.
#125000
b110 *"
b111 8"
0%"
03"
b0 ="
1E
b1000 ?
b1000 g
b0 9"
b0 =
b0 f
b0 2"
b101 K"
b110 d
b10 #
b10 H
b110010 $
b110010 G
0!
b11 :
b11 l
b11 J"
b0 I"
b0 H"
b100 ;
b100 m
b100 <"
b101 G"
b1 r
b1 :"
b1 @"
b0 n
b0 ."
b0 C"
b0 ,"
1.
#130000
0.
#135000
b10 z
b11 *"
b100 8"
1u
1%"
13"
b0 K"
0E
b1111 ?
b1111 g
b0 ;
b0 m
b0 <"
b0 G"
b0 r
b0 :"
b0 @"
b101 :
b101 l
b101 J"
b1 H"
b0 d
0R
1!
b11 "
b11 I
1.
#140000
0.
#145000
0!
b0 :
b0 l
b0 J"
b0 H"
1.
